README.md
setup.py
hanlp_restful/__init__.py
hanlp_restful.egg-info/PKG-INFO
hanlp_restful.egg-info/SOURCES.txt
hanlp_restful.egg-info/dependency_links.txt
hanlp_restful.egg-info/requires.txt
hanlp_restful.egg-info/top_level.txt
tests/test_client.py