Metadata-Version: 2.1
Name: hanlp_restful
Version: 0.0.24
Summary: HanLP: Han Language Processing
Home-page: https://github.com/hankcs/HanLP
Author: hankcs
Author-email: hankcshe@gmail.com
License: Apache License 2.0
Keywords: corpus,machine-learning,NLU,NLP
Classifier: Intended Audience :: Science/Research
Classifier: Intended Audience :: Developers
Classifier: Development Status :: 3 - Alpha
Classifier: Operating System :: OS Independent
Classifier: License :: OSI Approved :: Apache Software License
Classifier: Programming Language :: Python :: 3 :: Only
Classifier: Topic :: Scientific/Engineering :: Artificial Intelligence
Classifier: Topic :: Text Processing :: Linguistic
Requires-Python: >=3.6
Requires-Dist: hanlp_common
